skydive/__init__.py
skydive/alerts.py
skydive/auth.py
skydive/captures.py
skydive/encoder.py
skydive/graph.py
skydive/packet_injector.py
skydive/rules.py
skydive/wsshell.py
skydive/rest/__init__.py
skydive/rest/client.py
skydive/websocket/__init__.py
skydive/websocket/client.py
skydive_client-0.7.0.dist-info/LICENSE.txt
skydive_client-0.7.0.dist-info/METADATA
skydive_client-0.7.0.dist-info/WHEEL
skydive_client-0.7.0.dist-info/entry_points.txt
skydive_client-0.7.0.dist-info/top_level.txt
skydive_client-0.7.0.dist-info/RECORD
