Metadata-Version: 2.1
Name: skydive-client
Version: 0.7.0
Summary: Skydive Python client library
Home-page: http://github.com/skydive-project/skydive
Author: Sylvain Afchain
Author-email: safchain@gmail.com
License: Apache2
Platform: UNKNOWN
Classifier: Intended Audience :: Information Technology
Classifier: Intended Audience :: Developers
Classifier: License :: OSI Approved :: Apache Software License
Classifier: Operating System :: POSIX :: Linux
Classifier: Programming Language :: Python
Classifier: Programming Language :: Python :: 2
Classifier: Programming Language :: Python :: 2.7
Classifier: Programming Language :: Python :: 3
Classifier: Programming Language :: Python :: 3.4
Classifier: Programming Language :: Python :: 3.5
Requires-Dist: autobahn (>=0.17.1)
Requires-Dist: requests (>=2.14.2)
Requires-Dist: asyncio (>=3.4.3)
